leap.common-0.6.2-py2.7-nspkg.pth
leap/common/__init__.py
leap/common/_version.py
leap/common/ca_bundle.py
leap/common/cacert.pem
leap/common/certs.py
leap/common/check.py
leap/common/decorators.py
leap/common/files.py
leap/common/http.py
leap/common/mail.py
leap/common/plugins.py
leap/common/service_hooks.py
leap/common/zmq_utils.py
leap/common/config/__init__.py
leap/common/config/baseconfig.py
leap/common/config/flags.py
leap/common/config/pluggableconfig.py
leap/common/events/__init__.py
leap/common/events/auth.py
leap/common/events/catalog.py
leap/common/events/client.py
leap/common/events/errors.py
leap/common/events/flags.py
leap/common/events/server.py
leap/common/events/txclient.py
leap/common/events/zmq_components.py
leap/common/testing/__init__.py
leap/common/testing/basetest.py
leap/common/testing/cacert.pem
leap/common/testing/https_server.py
leap/common/testing/leaptest_combined_keycert.pem
leap/common/testing/leaptestscert.pem
leap/common/testing/leaptestskey.pem
leap.common-0.6.2.dist-info/DESCRIPTION.rst
leap.common-0.6.2.dist-info/METADATA
leap.common-0.6.2.dist-info/RECORD
leap.common-0.6.2.dist-info/WHEEL
leap.common-0.6.2.dist-info/metadata.json
leap.common-0.6.2.dist-info/namespace_packages.txt
leap.common-0.6.2.dist-info/top_level.txt
