Metadata-Version: 2.0
Name: leap.common
Version: 0.6.2
Summary: Common files used by the LEAP project.
Home-page: https://leap.se/
Author: Kali Kaneko
Author-email: kali@leap.se
License: GPLv3+
Download-URL: https://github.com/leapcode/bitmask_client/archive/0.6.2.tar.gz
Platform: UNKNOWN
Classifier: Development Status :: 3 - Alpha
Classifier: Intended Audience :: Developers
Classifier: License :: OSI Approved :: GNU General Public License v3 or later (GPLv3+)
Classifier: Operating System :: OS Independent
Classifier: Programming Language :: Python
Classifier: Programming Language :: Python :: 2.6
Classifier: Programming Language :: Python :: 2.7
Classifier: Topic :: Communications
Classifier: Topic :: Security
Classifier: Topic :: Utilities
Requires-Dist: jsonschema
Requires-Dist: pyopenssl
Requires-Dist: python-dateutil
Requires-Dist: pyzmq (>=14.4.1)
Requires-Dist: txzmq (>=0.7.3)
Provides-Extra: http
Requires-Dist: Twisted (>=14.0.2); extra == 'http'
Requires-Dist: certifi; extra == 'http'
Requires-Dist: service-identity; extra == 'http'
Requires-Dist: zope.interface; extra == 'http'
